{
    "total": [
        {
            "id": "100044481829323",
            "count": 20
        },
        {
            "id": "100069553397601",
            "count": 0
        },
        {
            "id": "100070633966285",
            "count": 27
        },
        {
            "id": "100071691251463",
            "count": 0
        },
        {
            "id": "100074047042302",
            "count": 0
        },
        {
            "id": "100074150424269",
            "count": 0
        },
        {
            "id": "100074480014436",
            "count": 0
        },
        {
            "id": "100074677144526",
            "count": 0
        },
        {
            "id": "100076603454951",
            "count": 0
        },
        {
            "id": "100078762117419",
            "count": 41
        },
        {
            "id": "100078942755682",
            "count": 6
        },
        {
            "id": "100079532412437",
            "count": 0
        },
        {
            "id": "100079889227489",
            "count": 0
        },
        {
            "id": "100080385603510",
            "count": 0
        },
        {
            "id": "100080423329373",
            "count": 0
        },
        {
            "id": "100080744207027",
            "count": 0
        },
        {
            "id": "100081087009935",
            "count": 33
        },
        {
            "id": "100082355345525",
            "count": 0
        },
        {
            "id": "100082614223874",
            "count": 0
        },
        {
            "id": "100083151172520",
            "count": 0
        },
        {
            "id": "100085283895602",
            "count": 0
        },
        {
            "id": "100086325892259",
            "count": 0
        },
        {
            "id": "100086499934101",
            "count": 1
        },
        {
            "id": "100087454234051",
            "count": 1
        }
    ],
    "week": [
        {
            "id": "100044481829323",
            "count": 0,
            "name": "Bùi MPhương"
        },
        {
            "id": "100069553397601",
            "count": 0,
            "name": "Học Vỉa"
        },
        {
            "id": "100070633966285",
            "count": 0,
            "name": "Cậubiếttingìchưa Phươngthèmbinhchiling"
        },
        {
            "id": "100071691251463",
            "count": 0,
            "name": "Vi Cá"
        },
        {
            "id": "100074047042302",
            "count": 0,
            "name": "Nguyệt Hipp"
        },
        {
            "id": "100074150424269",
            "count": 0,
            "name": "Đặng Đức Tuyểnn"
        },
        {
            "id": "100074480014436",
            "count": 0,
            "name": "Ngô Nqocc Anhh"
        },
        {
            "id": "100074677144526",
            "count": 0,
            "name": "Vi Hồng Ngọc"
        },
        {
            "id": "100076603454951",
            "count": 0,
            "name": "NT Ngocc Anhh"
        },
        {
            "id": "100078762117419",
            "count": 0,
            "name": "Ngoc Mai JW"
        },
        {
            "id": "100078942755682",
            "count": 0,
            "name": "Trần Thị Thanh"
        },
        {
            "id": "100079532412437",
            "count": 0,
            "name": "Nguyễn Thùy Dung"
        },
        {
            "id": "100079889227489",
            "count": 0,
            "name": "Người dùng Facebook"
        },
        {
            "id": "100080385603510",
            "count": 0,
            "name": "Giaa Huy"
        },
        {
            "id": "100080423329373",
            "count": 0,
            "name": "Nguyễn Văn Thành"
        },
        {
            "id": "100080744207027",
            "count": 0,
            "name": "Vi Thanh Thuyy"
        },
        {
            "id": "100081087009935",
            "count": 0,
            "name": "Quang Khải"
        },
        {
            "id": "100082355345525",
            "count": 0,
            "name": "Ng Hoa"
        },
        {
            "id": "100082614223874",
            "count": 0,
            "name": "Ngọc Diệp"
        },
        {
            "id": "100083151172520",
            "count": 0,
            "name": "凰爱凤"
        },
        {
            "id": "100085283895602",
            "count": 0,
            "name": "Ngọc Ánh"
        },
        {
            "id": "100086325892259",
            "count": 0,
            "name": "Lê Trung Hiếu"
        },
        {
            "id": "100086499934101",
            "count": 0,
            "name": "Thúy Kiều"
        },
        {
            "id": "100087454234051",
            "count": 0,
            "name": "Trangg Kieuu"
        }
    ],
    "day": [
        {
            "id": "100044481829323",
            "count": 0,
            "name": "Bùi MPhương"
        },
        {
            "id": "100069553397601",
            "count": 0,
            "name": "Học Vỉa"
        },
        {
            "id": "100070633966285",
            "count": 0,
            "name": "Cậubiếttingìchưa Phươngthèmbinhchiling"
        },
        {
            "id": "100071691251463",
            "count": 0,
            "name": "Vi Cá"
        },
        {
            "id": "100074047042302",
            "count": 0,
            "name": "Nguyệt Hipp"
        },
        {
            "id": "100074150424269",
            "count": 0,
            "name": "Đặng Đức Tuyểnn"
        },
        {
            "id": "100074480014436",
            "count": 0,
            "name": "Ngô Nqocc Anhh"
        },
        {
            "id": "100074677144526",
            "count": 0,
            "name": "Vi Hồng Ngọc"
        },
        {
            "id": "100076603454951",
            "count": 0,
            "name": "NT Ngocc Anhh"
        },
        {
            "id": "100078762117419",
            "count": 0,
            "name": "Ngoc Mai JW"
        },
        {
            "id": "100078942755682",
            "count": 0,
            "name": "Trần Thị Thanh"
        },
        {
            "id": "100079532412437",
            "count": 0,
            "name": "Nguyễn Thùy Dung"
        },
        {
            "id": "100079889227489",
            "count": 0,
            "name": "Người dùng Facebook"
        },
        {
            "id": "100080385603510",
            "count": 0,
            "name": "Giaa Huy"
        },
        {
            "id": "100080423329373",
            "count": 0,
            "name": "Nguyễn Văn Thành"
        },
        {
            "id": "100080744207027",
            "count": 0,
            "name": "Vi Thanh Thuyy"
        },
        {
            "id": "100081087009935",
            "count": 0,
            "name": "Quang Khải"
        },
        {
            "id": "100082355345525",
            "count": 0,
            "name": "Ng Hoa"
        },
        {
            "id": "100082614223874",
            "count": 0,
            "name": "Ngọc Diệp"
        },
        {
            "id": "100083151172520",
            "count": 0,
            "name": "凰爱凤"
        },
        {
            "id": "100085283895602",
            "count": 0,
            "name": "Ngọc Ánh"
        },
        {
            "id": "100086325892259",
            "count": 0,
            "name": "Lê Trung Hiếu"
        },
        {
            "id": "100086499934101",
            "count": 0,
            "name": "Thúy Kiều"
        },
        {
            "id": "100087454234051",
            "count": 0,
            "name": "Trangg Kieuu"
        }
    ],
    "time": 4
}